MANIFEST.in
README.txt
TODO.txt
VERSION.txt
setup.py
amplikyzer/__init__.py
amplikyzer/__main__.py
amplikyzer/align.py
amplikyzer/alphabets.py
amplikyzer/analysis.py
amplikyzer/core.py
amplikyzer/flowdna.py
amplikyzer/graphics.py
amplikyzer/main.py
amplikyzer/methylation.py
amplikyzer/printreads.py
amplikyzer/scoring.py
amplikyzer/sff.py
amplikyzer/statistics.py
amplikyzer/utils.py
amplikyzer.egg-info/PKG-INFO
amplikyzer.egg-info/SOURCES.txt
amplikyzer.egg-info/dependency_links.txt
amplikyzer.egg-info/requires.txt
amplikyzer.egg-info/top_level.txt
bin/amplikyzer
bin/amplikyzergui
bin/show-nonascii.py